schedulerlock/__init__.py
schedulerlock/admin.py
schedulerlock/apps.py
schedulerlock/jobs/all_jobs.py
schedulerlock/jobs/scheduler_lock_job.py
schedulerlock/locks/base_lock.py
schedulerlock/locks/database_advisory_lock.py
schedulerlock/locks/database_lock.original
schedulerlock/locks/database_lock.py
schedulerlock/locks/file_lock.py
schedulerlock/locks/queries.py
schedulerlock/locks/utils.py
schedulerlock/migrations/0001_initial.py
schedulerlock/migrations/__init__.py
schedulerlock/models.py
schedulerlock/tests.py
schedulerlock/urls.py
schedulerlock/views.py
schedulerlock-0.1.4.dist-info/WHEEL
schedulerlock-0.1.4.dist-info/METADATA
schedulerlock-0.1.4.dist-info/RECORD
