Metadata-Version: 2.1
Name: schedulerlock
Version: 0.1.4
Summary: 
Author: Soham Marik
Author-email: soham.marik@automationedge.com
Requires-Python: >=3.9,<4.0
Classifier: Programming Language :: Python :: 3
Classifier: Programming Language :: Python :: 3.10
Classifier: Programming Language :: Python :: 3.9
Requires-Dist: Django (==3.2.6)
Requires-Dist: django-apscheduler (==0.6.2)
